{
    "AK620G2单F9 R120": [
        [
            57.0,
            51.6,
            2991.0
        ],
        [
            50.0,
            53.0,
            2332.0
        ],
        [
            44.9,
            54.7,
            1896.0
        ],
        [
            40.0,
            56.6,
            1564.0
        ]
    ],
    "AK620G2双F9 R120": [
        [
            60.4,
            50.3,
            3062.0
        ],
        [
            50.0,
            51.7,
            2139.0
        ],
        [
            44.9,
            53.1,
            1744.0
        ],
        [
            40.0,
            54.9,
            1438.0
        ]
    ],
    "AK620G2三F9 R120": [
        [
            61.7,
            49.2,
            3069.0
        ],
        [
            50.0,
            50.8,
            2065.0
        ],
        [
            44.8,
            51.9,
            1668.0
        ],
        [
            40.1,
            53.4,
            1410.0
        ]
    ],
    "P60T Ultra单莫比乌斯": [
        [
            43.8,
            56.3,
            2366.0
        ],
        [
            39.2,
            57.8,
            1964.0
        ]
    ],
    "P60T Ultra双莫比乌斯": [
        [
            46.2,
            54.7,
            2370.0
        ],
        [
            40.1,
            56.2,
            1896.0
        ]
    ],
    "P60T Ultra三莫比乌斯": [
        [
            47.5,
            54.3,
            2384.0
        ],
        [
            40.0,
            56.1,
            1789.0
        ]
    ],
    "AK620G2单莫比乌斯": [
        [
            43.9,
            54.8,
            2392.0
        ],
        [
            39.9,
            55.7,
            2027.0
        ]
    ],
    "AK620G2双莫比乌斯": [
        [
            46.7,
            52.4,
            2384.0
        ],
        [
            40.0,
            54.2,
            1835.0
        ]
    ],
    "AK620G2三莫比乌斯": [
        [
            47.9,
            52.1,
            2381.0
        ],
        [
            40.0,
            53.7,
            1771.0
        ]
    ]
}